pyticketfood/__init__.py
pyticketfood/manager.py
pyticketfood/ticket.py
pyticketfood-0.2.0.dist-info/LICENSE.txt
pyticketfood-0.2.0.dist-info/METADATA
pyticketfood-0.2.0.dist-info/WHEEL
pyticketfood-0.2.0.dist-info/top_level.txt
pyticketfood-0.2.0.dist-info/RECORD
